aitkit/__init__.py
aitkit/corpora/__init__.py
aitkit/corpora/abstract_dictionary.py
aitkit/corpora/abstract_document_collection.py
aitkit/corpora/dictionary.py
aitkit/corpora/doc_collection.py
aitkit/models/__init__.py
aitkit/models/ontology_tagging.py
aitkit/models/phrase_model.py
aitkit/models/rule_tagging.py
aitkit/models/shingle_model.py
aitkit/models/textprocessor.py
aitkit/testdata/__init__.py
aitkit/testdata/onegin.py
aitkit/utils/__init__.py
aitkit/utils/array_tools.py
aitkit/utils/compare_funcs.py
aitkit/utils/random.py
aitkit/utils/save_load.py
aitkit-0.0.11.dist-info/METADATA
aitkit-0.0.11.dist-info/WHEEL
aitkit-0.0.11.dist-info/top_level.txt
aitkit-0.0.11.dist-info/zip-safe
aitkit-0.0.11.dist-info/RECORD
