Metadata-Version: 2.1
Name: aitkit
Version: 0.0.11
Summary: AI processing toolkit
Home-page: UNKNOWN
Author: aimasters team
Author-email: kavcevich@action-media.ru
License: UNKNOWN
Platform: UNKNOWN
